bach-0.1b6.dist-info/zip-safe
bach-0.1b6.dist-info/WHEEL
bach-0.1b6.dist-info/METADATA
bach-0.1b6.dist-info/metadata.json
bach-0.1b6.dist-info/top_level.txt
bach-0.1b6.dist-info/DESCRIPTION.rst
bach-0.1b6.dist-info/RECORD
bach/__init__.py
bach/bach.py
bach/io.py
bach/unpack.py
bach/translate/__init__.py
bach/translate/xml.py
