Metadata-Version: 2.0
Name: bach
Version: 0.1b6
Summary: An XML-interoperable general-purpose semantic document markup language*
Home-page: https://github.com/tawesoft/bach
Author: Tawesoft Ltd
Author-email: opensource@tawesoft.co.uk
License: MIT
Platform: UNKNOWN
Classifier: Development Status :: 4 - Beta
Classifier: Intended Audience :: Developers
Classifier: License :: OSI Approved
Classifier: Programming Language :: Python :: 3
Classifier: Programming Language :: Python :: 3.4
Classifier: Topic :: Software Development :: Libraries :: Python Modules
Classifier: Topic :: Documentation
Classifier: Topic :: Office/Business
Classifier: Topic :: Software Development :: Interpreters
Classifier: Topic :: Text Processing :: Markup
Classifier: Topic :: Text Processing :: Markup :: XML
